odoo/addons/contract_split/README.rst
odoo/addons/contract_split/__init__.py
odoo/addons/contract_split/__manifest__.py
odoo/addons/contract_split/i18n/contract_split.pot
odoo/addons/contract_split/i18n/es.po
odoo/addons/contract_split/i18n/fr_FR.po
odoo/addons/contract_split/i18n/it.po
odoo/addons/contract_split/models/__init__.py
odoo/addons/contract_split/models/contract.py
odoo/addons/contract_split/readme/CONTRIBUTORS.rst
odoo/addons/contract_split/readme/DESCRIPTION.rst
odoo/addons/contract_split/readme/ROADMAP.rst
odoo/addons/contract_split/readme/USAGE.rst
odoo/addons/contract_split/security/ir.model.access.csv
odoo/addons/contract_split/static/description/icon.png
odoo/addons/contract_split/static/description/index.html
odoo/addons/contract_split/tests/__init__.py
odoo/addons/contract_split/tests/test_contract_split.py
odoo/addons/contract_split/views/contract.xml
odoo/addons/contract_split/wizard/__init__.py
odoo/addons/contract_split/wizard/wizard_split_contract.py
odoo/addons/contract_split/wizard/wizard_split_contract.xml
odoo14_addon_contract_split-14.0.1.0.1.dev17.dist-info/METADATA
odoo14_addon_contract_split-14.0.1.0.1.dev17.dist-info/WHEEL
odoo14_addon_contract_split-14.0.1.0.1.dev17.dist-info/top_level.txt
odoo14_addon_contract_split-14.0.1.0.1.dev17.dist-info/RECORD
